trtutils/__init__.py
trtutils/__main__.py
trtutils/_benchmark.py
trtutils/_config.py
trtutils/_engine.py
trtutils/_flags.py
trtutils/_jit.py
trtutils/_log.py
trtutils/_model.py
trtutils/py.typed
trtutils/builder/__init__.py
trtutils/builder/_batcher.py
trtutils/builder/_build.py
trtutils/builder/_calibrator.py
trtutils/builder/_dla.py
trtutils/builder/_onnx.py
trtutils/builder/_progress.py
trtutils/builder/_utils.py
trtutils/core/__init__.py
trtutils/core/_bindings.py
trtutils/core/_context.py
trtutils/core/_cuda.py
trtutils/core/_engine.py
trtutils/core/_interface.py
trtutils/core/_kernels.py
trtutils/core/_lock.py
trtutils/core/_memory.py
trtutils/core/_nvrtc.py
trtutils/core/_stream.py
trtutils/core/cache.py
trtutils/core/_engine_cache/__init__.py
trtutils/impls/__init__.py
trtutils/impls/common.py
trtutils/impls/kernels.py
trtutils/impls/onnx_models.py
trtutils/impls/_kernels/letterbox.cu
trtutils/impls/_kernels/linear.cu
trtutils/impls/_kernels/sst.cu
trtutils/impls/_kernels/sst_opt.cu
trtutils/impls/_onnx/yolo_preproc_base.onnx
trtutils/impls/yolo/__init__.py
trtutils/impls/yolo/__main__.py
trtutils/impls/yolo/_parallel.py
trtutils/impls/yolo/_process.py
trtutils/impls/yolo/_run.py
trtutils/impls/yolo/_yolo.py
trtutils/impls/yolo/_yolos.py
trtutils/impls/yolo/_preprocessors/__init__.py
trtutils/impls/yolo/_preprocessors/_cpu.py
trtutils/impls/yolo/_preprocessors/_cuda.py
trtutils/impls/yolo/_preprocessors/_trt.py
trtutils/inspect/__init__.py
trtutils/inspect/_inspect.py
trtutils/inspect/_names.py
trtutils/jetson/__init__.py
trtutils/jetson/_benchmark.py
trtutils/trtexec/__init__.py
trtutils/trtexec/__main__.py
trtutils/trtexec/_build.py
trtutils/trtexec/_cli.py
trtutils/trtexec/_find.py
trtutils/trtexec/_run.py
trtutils-0.6.1.dist-info/licenses/LICENSE
trtutils-0.6.1.dist-info/METADATA
trtutils-0.6.1.dist-info/WHEEL
trtutils-0.6.1.dist-info/top_level.txt
trtutils-0.6.1.dist-info/RECORD
