Metadata-Version: 2.4
Name: trtutils
Version: 0.6.1
Summary: Utilities for making TensorRT easier to use
Author-email: Justin Davis <davisjustin302@gmail.com>
Maintainer-email: Justin Davis <davisjustin302@gmail.com>
Project-URL: Homepage, https://github.com/justincdavis/trtutils
Project-URL: Bug Tracker, https://github.com/justincdavis/trtutils/issues
Classifier: Development Status :: 4 - Beta
Classifier: Programming Language :: Python :: 3 :: Only
Classifier: Programming Language :: Python :: 3
Classifier: Programming Language :: Python :: 3.8
Classifier: Programming Language :: Python :: 3.9
Classifier: Programming Language :: Python :: 3.10
Classifier: Programming Language :: Python :: 3.11
Classifier: Programming Language :: Python :: 3.12
Classifier: Programming Language :: Python :: 3.13
Classifier: Programming Language :: Python :: Implementation :: CPython
Classifier: License :: OSI Approved :: MIT License
Classifier: Operating System :: Microsoft :: Windows
Classifier: Operating System :: POSIX :: Linux
Classifier: Natural Language :: English
Classifier: Topic :: System :: Hardware
Classifier: Topic :: Scientific/Engineering
Classifier: Topic :: Scientific/Engineering :: Artificial Intelligence
Classifier: Topic :: Scientific/Engineering :: Image Processing
Classifier: Topic :: Scientific/Engineering :: Image Recognition
Classifier: Topic :: Software Development
Classifier: Topic :: Software Development :: Embedded Systems
Classifier: Topic :: Software Development :: Libraries
Classifier: Intended Audience :: Developers
Classifier: Intended Audience :: Education
Classifier: Intended Audience :: Science/Research
Classifier: Intended Audience :: Education
Classifier: Intended Audience :: End Users/Desktop
Classifier: Typing :: Typed
Requires-Python: <=3.14,>=3.8
License-File: LICENSE
Requires-Dist: tensorrt>=8.0.0
Requires-Dist: cuda-python>=8.0.0
Requires-Dist: numpy<2.2.0,>=1.19.0
Requires-Dist: cv2ext>=0.1.0
Requires-Dist: opencv-python>=4.8.0
Requires-Dist: jetsontools>=0.1.0
Requires-Dist: tqdm>=4.67.1
Requires-Dist: typing_extensions>=4.0.0
Provides-Extra: all
Requires-Dist: trtutils[jit]; extra == "all"
Provides-Extra: jit
Requires-Dist: numba>=0.57.0; extra == "jit"
Provides-Extra: benchmark
Requires-Dist: torch>=2.0.0; extra == "benchmark"
Requires-Dist: ultralytics>=8.3.100; extra == "benchmark"
Requires-Dist: onnx>=1.14.0; extra == "benchmark"
Requires-Dist: onnxslim>=0.1.20; extra == "benchmark"
Requires-Dist: matplotlib>=3.0.0; extra == "benchmark"
Provides-Extra: ci
Requires-Dist: ruff>=0.11.13; extra == "ci"
Requires-Dist: mypy>=1.16.0; extra == "ci"
Requires-Dist: types-tqdm>=4.67; extra == "ci"
Provides-Extra: test
Requires-Dist: pytest>=6.2.0; extra == "test"
Provides-Extra: docs
Requires-Dist: sphinx>=7.0.0; extra == "docs"
Requires-Dist: sphinx_design>=0.6.1; extra == "docs"
Requires-Dist: furo>=2024.8.6; extra == "docs"
Requires-Dist: myst_parser>=4.0.0; extra == "docs"
Requires-Dist: matplotlib>=3.0.0; extra == "docs"
Provides-Extra: dev
Requires-Dist: trtutils[ci]; extra == "dev"
Requires-Dist: trtutils[test]; extra == "dev"
Requires-Dist: trtutils[docs]; extra == "dev"
Requires-Dist: twine>=4.0.0; extra == "dev"
Requires-Dist: wheel>=0.37.0; extra == "dev"
Requires-Dist: bumpver>=2023.1126; extra == "dev"
Requires-Dist: pyclean>=2.7.0; extra == "dev"
Requires-Dist: pyright>=1.1.348; extra == "dev"
Dynamic: license-file
